ru_sent_tokenize/__init__.py
ru_sent_tokenize/tokenizer.py
rusenttokenize/__init__.py
rusenttokenize/tokenizer.py
rusenttokenize-0.0.5.dist-info/METADATA
rusenttokenize-0.0.5.dist-info/RECORD
rusenttokenize-0.0.5.dist-info/WHEEL
rusenttokenize-0.0.5.dist-info/top_level.txt
tests/__init__.py
tests/test_tokenizer.py
