Metadata-Version: 2.1
Name: rusenttokenize
Version: 0.0.5
Summary: Rule-based sentence tokenizer for Russian language
Home-page: https://github.com/deepmipt/ru_sentence_tokenizer
Author: Marat Zaynutdinov
Author-email: tsundokum@gmail.com
License: UNKNOWN
Platform: UNKNOWN
Classifier: Programming Language :: Python :: 3
Classifier: License :: OSI Approved :: Apache Software License
Classifier: Operating System :: OS Independent
